CHANGELOG.md
LICENSE
pygpseq/__init__.py
pygpseq/anim/__init__.py
pygpseq/anim/analysis.py
pygpseq/anim/condition.py
pygpseq/anim/main.py
pygpseq/anim/nucleus.py
pygpseq/anim/series.py
pygpseq/const.py
pygpseq/fish/__init__.py
pygpseq/fish/dot.py
pygpseq/fish/image.py
pygpseq/fish/nucleus.py
pygpseq/scripts/__init__.py
pygpseq/scripts/czi_to_tiff.py
pygpseq/scripts/gpseq_anim.py
pygpseq/scripts/gpseq_fromfish.py
pygpseq/scripts/gpseq_fromfish_merge.py
pygpseq/scripts/nd2_to_tiff.py
pygpseq/scripts/tiff_auto3dseg.py
pygpseq/scripts/tiff_desplit.py
pygpseq/scripts/tiff_findoof.py
pygpseq/scripts/tiff_split.py
pygpseq/scripts/tiffcu.py
pygpseq/static/report_template.html
pygpseq/tools/__init__.py
pygpseq/tools/binarize.py
pygpseq/tools/chromab.py
pygpseq/tools/distance.py
pygpseq/tools/image.py
pygpseq/tools/io.py
pygpseq/tools/path.py
pygpseq/tools/plot.py
pygpseq/tools/stat.py
pygpseq/tools/string.py
pygpseq/tools/vector.py
pygpseq-3.4.1.dist-info/entry_points.txt
pygpseq-3.4.1.dist-info/LICENSE
pygpseq-3.4.1.dist-info/WHEEL
pygpseq-3.4.1.dist-info/METADATA
pygpseq-3.4.1.dist-info/RECORD
