Metadata-Version: 2.1
Name: pygpseq
Version: 3.4.1
Summary: A GPSeq image analysis package
Home-page: https://github.com/ggirelli/pygpseq
License: MIT
Keywords: microscopy,image,analysis,bioimaging,nucleus,segmentation,conversion
Author: Gabriele Girelli
Author-email: gigi.ga90@gmail.com
Requires-Python: >=3.6,<3.7
Classifier: Development Status :: 5 - Production/Stable
Classifier: Environment :: Console
Classifier: Intended Audience :: Science/Research
Classifier: License :: OSI Approved :: MIT License
Classifier: Operating System :: POSIX :: Linux
Classifier: Operating System :: Unix
Classifier: Programming Language :: Python :: 3
Classifier: Programming Language :: Python :: 3.6
Classifier: Topic :: Scientific/Engineering :: Bio-Informatics
Requires-Dist: Cython (==0.29.5)
Requires-Dist: Jinja2 (==2.11.3)
Requires-Dist: czifile (==0.1.5)
Requires-Dist: ggc (==0.0.3)
Requires-Dist: joblib (==0.11)
Requires-Dist: matplotlib (==2.2.2)
Requires-Dist: nd2reader (==3.1.0)
Requires-Dist: numpy (==1.16.1)
Requires-Dist: pandas (==0.24.1)
Requires-Dist: scikit-image (==0.14.2)
Requires-Dist: scipy (==1.2.1)
Requires-Dist: seaborn (==0.9.0)
Requires-Dist: tifffile (==2019.2.10)
Requires-Dist: tqdm (==4.31.1)
Requires-Dist: weasyprint (==45)
Project-URL: Repository, https://github.com/ggirelli/pygpseq
